jl_exp_deconv/__init__.py
jl_exp_deconv/due.py
jl_exp_deconv/error_metrics.py
jl_exp_deconv/jl_exp_deconv.py
jl_exp_deconv/plotting_tools.py
jl_exp_deconv/version.py
jl_exp_deconv/data/0.2M equimolar mixture of HMF + fru+ La+Fa diff number of scans.xlsx
"jl_exp_deconv/data/081419 Mixes (0.45,0.4,0.3,0.25).xlsx"
jl_exp_deconv/data/082019 0.15 M Hcl +0.3M fru FULL DEHYDRATION.xlsx
jl_exp_deconv/data/082819 Mixes varied concentrations.xlsx
"jl_exp_deconv/data/090319 Full dehydrations, high fructose, 0.15 and 0.25 M HCl.xlsx"
jl_exp_deconv/data/Formic Acid.xlsx
jl_exp_deconv/data/Fructose Curve.xlsx
jl_exp_deconv/data/HMF Curve.xlsx
jl_exp_deconv/data/IR Mix Josh-with sample concentrations.xlsx
jl_exp_deconv/data/Levulinic Acid.xlsx
jl_exp_deconv/data/Test1-0.5M.xlsx
jl_exp_deconv/data/Test4-0.05M.xlsx
jl_exp_deconv/data/mixed_components/Mix1.csv
jl_exp_deconv/data/mixed_components/Mix2.csv
jl_exp_deconv/data/mixed_components/Mix3.csv
jl_exp_deconv/data/mixed_components/Mix4.csv
jl_exp_deconv/data/mixed_components/Mix5.csv
jl_exp_deconv/data/mixed_components/Mix6.csv
jl_exp_deconv/data/mixed_components/Mix7.csv
jl_exp_deconv/data/mixed_components/Test1-0.5M.csv
jl_exp_deconv/data/mixed_components/Test1=F+HMF+LA+FA.csv
jl_exp_deconv/data/mixed_components/Test2=2F+HMF+LA+FA.csv
jl_exp_deconv/data/mixed_components/Test3=F+2HMF+LA+FA.csv
jl_exp_deconv/data/mixed_components/Test4-0.05M.csv
jl_exp_deconv/data/mixed_components/Test4=F+HMF+2LA+FA.csv
jl_exp_deconv/data/mixed_components/Test5=F+HMF+LA+2FA.csv
jl_exp_deconv/data/pure_components/Formic_Acid_DATA.csv
jl_exp_deconv/data/pure_components/Fructose_DATA.csv
jl_exp_deconv/data/pure_components/HMF_DATA.csv
jl_exp_deconv/data/pure_components/Levulinic_Acid_DATA.csv
jl_exp_deconv/data/reaction/082019 0.15 M Hcl +0.3M fru FULL DEHYDRATION.csv
"jl_exp_deconv/data/reaction/090319 Full dehydrations, high fructose, 0.15 and 0.25 M HCl.csv"
jl_exp_deconv/tests/__init__.py
jl_exp_deconv/tests/test_jl_exp_deconv.py
jl_exp_deconv-0.4.dist-info/LICENSE
jl_exp_deconv-0.4.dist-info/METADATA
jl_exp_deconv-0.4.dist-info/WHEEL
jl_exp_deconv-0.4.dist-info/top_level.txt
jl_exp_deconv-0.4.dist-info/RECORD
