Metadata-Version: 2.1
Name: jl-exp-deconv
Version: 0.4
Summary: jl_exp_deconv: A method for deconvoluting spectra
Home-page: http://github.com/JLANS/jl_exp_deconv
Author: Joshua Lansford
Author-email: lansford.jl@gmail.com
Maintainer: Joshua Lansford
Maintainer-email: lansford.jl@gmail.com
License: MIT
Platform: OS Independent
Classifier: Development Status :: 3 - Alpha
Classifier: Environment :: Console
Classifier: Intended Audience :: Science/Research
Classifier: License :: OSI Approved :: MIT License
Classifier: Operating System :: OS Independent
Classifier: Programming Language :: Python
Classifier: Topic :: Scientific/Engineering
Requires-Python: >= 3.5
Requires-Dist: numpy
Requires-Dist: scipy
Requires-Dist: matplotlib
